README.md
setup.py
yue/__init__.py
yue/test.py
yue/tmp.py
yue/wn.py
yue/wu.py
yue/wy.py
yue.egg-info/PKG-INFO
yue.egg-info/SOURCES.txt
yue.egg-info/dependency_links.txt
yue.egg-info/requires.txt
yue.egg-info/top_level.txt